distsuper/__init__.py
distsuper/common/__init__.py
distsuper/common/exceptions.py
distsuper/common/handlers.py
distsuper/common/tools.py
distsuper/configure/__init__.py
distsuper/configure/distsuper.ini
distsuper/main/__init__.py
distsuper/main/load.py
distsuper/main/local.py
distsuper/main/remote.py
distsuper/main/shell.py
distsuper/models/__init__.py
distsuper/models/models.py
distsuper/scripts/__init__.py
distsuper/scripts/common.py
distsuper/scripts/distsuperagent.py
distsuper/scripts/distsuperctl.py
distsuper/scripts/distsuperd.py
distsuper/web/__init__.py
distsuper/web/agent.py
distsuper/web/common/__init__.py
distsuper/web/common/processwrapper.py
distsuper-0.1.0.dist-info/METADATA
distsuper-0.1.0.dist-info/RECORD
distsuper-0.1.0.dist-info/WHEEL
distsuper-0.1.0.dist-info/entry_points.txt
distsuper-0.1.0.dist-info/top_level.txt
