Metadata-Version: 2.1
Name: distsuper
Version: 0.1.0
Summary: 仿照supervisor的功能实现的一个分布式进程监控工具，支持跨机器的进程失效转移
Home-page: https://github.com/lrbsunday/distsuper
Author: lrbsunday
Author-email: 272316131@qq.com
Maintainer: lrbsunday
Maintainer-email: 272316131@qq.com
License: UNKNOWN
Platform: UNKNOWN
Requires-Dist: pymysql
Requires-Dist: requests
Requires-Dist: uwsgi
Requires-Dist: flask
Requires-Dist: peewee
Requires-Dist: click
